{
	"info": {
		"_postman_id": "90836daa-b738-4745-9b0e-e8d6332f04d4",
		"name": "Grupo01",
		"schema": "https://schema.getpostman.com/json/collection/v2.1.0/collection.json",
		"_exporter_id": "21597864"
	},
	"item": [
		{
			"name": "Pedido",
			"item": [
				{
					"name": "GetById",
					"request": {
						"method": "GET",
						"header": [],
						"url": {
							"raw": "https://localhost:8080/Pedido/1",
							"protocol": "https",
							"host": [
								"localhost"
							],
							"port": "8080",
							"path": [
								"Pedido",
								"1"
							]
						}
					},
					"response": []
				},
				{
					"name": "GetByIdStatus",
					"request": {
						"method": "GET",
						"header": [],
						"url": {
							"raw": "https://localhost:8080/Pedido/Status/1",
							"protocol": "https",
							"host": [
								"localhost"
							],
							"port": "8080",
							"path": [
								"Pedido",
								"Status",
								"1"
							]
						}
					},
					"response": []
				},
				{
					"name": "Create",
					"request": {
						"method": "POST",
						"header": [],
						"body": {
							"mode": "raw",
							"raw": "{\r\n  \"idCliente\": 1,\r\n  \"produtosPedido\": [\r\n    {\r\n      \"idProduto\": 1,\r\n      \"quantidade\": 2\r\n    },\r\n    {\r\n      \"idProduto\": 3,\r\n      \"quantidade\": 4\r\n    }\r\n  ]\r\n}",
							"options": {
								"raw": {
									"language": "json"
								}
							}
						},
						"url": {
							"raw": "https://localhost:8080/Pedido",
							"protocol": "https",
							"host": [
								"localhost"
							],
							"port": "8080",
							"path": [
								"Pedido"
							]
						}
					},
					"response": []
				},
				{
					"name": "Update",
					"request": {
						"method": "PUT",
						"header": [],
						"body": {
							"mode": "raw",
							"raw": "{\r\n  \"idPedido\": 1,\r\n  \"produtosPedido\": [\r\n    {\r\n      \"idProduto\": 2,\r\n      \"quantidade\": 3\r\n    }\r\n  ]\r\n}",
							"options": {
								"raw": {
									"language": "json"
								}
							}
						},
						"url": {
							"raw": "https://localhost:8080/Pedido",
							"protocol": "https",
							"host": [
								"localhost"
							],
							"port": "8080",
							"path": [
								"Pedido"
							]
						}
					},
					"response": []
				},
				{
					"name": "UpdateStatus",
					"request": {
						"method": "PUT",
						"header": [],
						"url": {
							"raw": "https://localhost:8080/Pedido/PedidoStatus?idPedido=1&idStatus=2",
							"protocol": "https",
							"host": [
								"localhost"
							],
							"port": "8080",
							"path": [
								"Pedido",
								"PedidoStatus"
							],
							"query": [
								{
									"key": "idPedido",
									"value": "1"
								},
								{
									"key": "idStatus",
									"value": "2"
								}
							]
						}
					},
					"response": []
				}
			]
		},
		{
			"name": "Categoria",
			"item": [
				{
					"name": "GetALL",
					"request": {
						"method": "GET",
						"header": [],
						"url": {
							"raw": "http://localhost:8080/Categoria",
							"protocol": "http",
							"host": [
								"localhost"
							],
							"port": "8080",
							"path": [
								"Categoria"
							]
						}
					},
					"response": []
				},
				{
					"name": "Create",
					"request": {
						"method": "POST",
						"header": [],
						"body": {
							"mode": "raw",
							"raw": "  {\r\n    \"idCategoria\": 0,\r\n    \"nome\": \"Saladas Especiais\"\r\n  }",
							"options": {
								"raw": {
									"language": "json"
								}
							}
						},
						"url": {
							"raw": "http://localhost:8080/Categoria",
							"protocol": "http",
							"host": [
								"localhost"
							],
							"port": "8080",
							"path": [
								"Categoria"
							]
						}
					},
					"response": []
				},
				{
					"name": "GetByID",
					"request": {
						"method": "GET",
						"header": [],
						"url": {
							"raw": "http://localhost:8080/Categoria/1",
							"protocol": "http",
							"host": [
								"localhost"
							],
							"port": "8080",
							"path": [
								"Categoria",
								"1"
							]
						}
					},
					"response": []
				},
				{
					"name": "Update",
					"request": {
						"method": "PUT",
						"header": [],
						"body": {
							"mode": "raw",
							"raw": "  {\r\n    \"idCategoria\": 0,\r\n    \"nome\": \"Salada Especial\"\r\n  }",
							"options": {
								"raw": {
									"language": "json"
								}
							}
						},
						"url": {
							"raw": "http://localhost:8080/Categoria/5",
							"protocol": "http",
							"host": [
								"localhost"
							],
							"port": "8080",
							"path": [
								"Categoria",
								"5"
							]
						}
					},
					"response": []
				},
				{
					"name": "Delete",
					"request": {
						"method": "DELETE",
						"header": [],
						"url": {
							"raw": "http://localhost:8080/Categoria/5",
							"protocol": "http",
							"host": [
								"localhost"
							],
							"port": "8080",
							"path": [
								"Categoria",
								"5"
							]
						}
					},
					"response": []
				}
			]
		},
		{
			"name": "Produto",
			"item": [
				{
					"name": "GetALL",
					"request": {
						"method": "GET",
						"header": [],
						"url": {
							"raw": "http://localhost:8080/Produto",
							"protocol": "http",
							"host": [
								"localhost"
							],
							"port": "8080",
							"path": [
								"Produto"
							]
						}
					},
					"response": []
				},
				{
					"name": "Create",
					"request": {
						"method": "POST",
						"header": [],
						"body": {
							"mode": "raw",
							"raw": "{\r\n  \"idProduto\": 0,\r\n  \"nome\": \"Sundae de Morango\",\r\n  \"descricao\": \"Sobremesa de Morango\",\r\n  \"preco\": 3.99,\r\n  \"urlImagem\": \"https://example.com/imagem78.jpg\",\r\n  \"idCategoria\": 4,\r\n  \"categoria\": \"Sobremesa\"\r\n}",
							"options": {
								"raw": {
									"language": "json"
								}
							}
						},
						"url": {
							"raw": "http://localhost:8080/Produto",
							"protocol": "http",
							"host": [
								"localhost"
							],
							"port": "8080",
							"path": [
								"Produto"
							]
						}
					},
					"response": []
				},
				{
					"name": "GetByID",
					"request": {
						"method": "GET",
						"header": [],
						"url": {
							"raw": "http://localhost:8080/Produto/1",
							"protocol": "http",
							"host": [
								"localhost"
							],
							"port": "8080",
							"path": [
								"Produto",
								"1"
							]
						}
					},
					"response": []
				},
				{
					"name": "Update",
					"request": {
						"method": "PUT",
						"header": [],
						"body": {
							"mode": "raw",
							"raw": "{\r\n    \"idProduto\": 0,\r\n    \"nome\": \"Hambúrguer\",\r\n    \"descricao\": \"Hambúrguer delicioso\",\r\n    \"preco\": 12.99,\r\n    \"urlImagem\": \"https://example.com/imagem1.jpg\",\r\n    \"idCategoria\": 1,\r\n    \"categoria\": \"Lanche\"\r\n}",
							"options": {
								"raw": {
									"language": "json"
								}
							}
						},
						"url": {
							"raw": "http://localhost:8080/Produto/1",
							"protocol": "http",
							"host": [
								"localhost"
							],
							"port": "8080",
							"path": [
								"Produto",
								"1"
							]
						}
					},
					"response": []
				},
				{
					"name": "Delete",
					"request": {
						"method": "DELETE",
						"header": [],
						"url": {
							"raw": "http://localhost:8080/Produto/31",
							"protocol": "http",
							"host": [
								"localhost"
							],
							"port": "8080",
							"path": [
								"Produto",
								"31"
							]
						}
					},
					"response": []
				},
				{
					"name": "GetByIDCategoria",
					"request": {
						"method": "GET",
						"header": [],
						"url": {
							"raw": "http://localhost:8080/Produto/Categoria/1",
							"protocol": "http",
							"host": [
								"localhost"
							],
							"port": "8080",
							"path": [
								"Produto",
								"Categoria",
								"2"
							]
						}
					},
					"response": []
				}
			]
		},
		{
			"name": "Acompanhamento",
			"item": [
				{
					"name": "GetALL",
					"request": {
						"method": "GET",
						"header": [],
						"url": {
							"raw": "http://localhost:8080/Acompanhamento",
							"protocol": "http",
							"host": [
								"localhost"
							],
							"port": "8080",
							"path": [
								"Acompanhamento"
							]
						}
					},
					"response": []
				},
				{
					"name": "Create",
					"request": {
						"method": "POST",
						"header": [],
						"body": {
							"mode": "raw",
							"raw": "  {\r\n    \"idAcompanhamento\": 0,\r\n    \"nome\": \"Novo Status\"\r\n  }",
							"options": {
								"raw": {
									"language": "json"
								}
							}
						},
						"url": {
							"raw": "http://localhost:8080/Acompanhamento",
							"protocol": "http",
							"host": [
								"localhost"
							],
							"port": "8080",
							"path": [
								"Acompanhamento"
							]
						}
					},
					"response": []
				},
				{
					"name": "GetByID",
					"request": {
						"method": "GET",
						"header": [],
						"url": {
							"raw": "http://localhost:8080/Acompanhamento/5",
							"protocol": "http",
							"host": [
								"localhost"
							],
							"port": "8080",
							"path": [
								"Acompanhamento",
								"5"
							]
						}
					},
					"response": []
				},
				{
					"name": "Update",
					"request": {
						"method": "PUT",
						"header": [],
						"body": {
							"mode": "raw",
							"raw": "  {\r\n    \"idAcompanhamento\": 0,\r\n    \"nome\": \"Status\"\r\n  }",
							"options": {
								"raw": {
									"language": "json"
								}
							}
						},
						"url": {
							"raw": "http://localhost:8080/Acompanhamento/5",
							"protocol": "http",
							"host": [
								"localhost"
							],
							"port": "8080",
							"path": [
								"Acompanhamento",
								"5"
							]
						}
					},
					"response": []
				},
				{
					"name": "Delete",
					"request": {
						"method": "DELETE",
						"header": [],
						"url": {
							"raw": "http://localhost:8080/Acompanhamento/5",
							"protocol": "http",
							"host": [
								"localhost"
							],
							"port": "8080",
							"path": [
								"Acompanhamento",
								"5"
							]
						}
					},
					"response": []
				}
			]
		}
	]
}